jlogr-0.1.233.dist-info/METADATA
jlogr-0.1.233.dist-info/WHEEL
jlogr/__init__.py
jlogr/py.typed
jlogr/jlogr.pyi
jlogr/jlogr.abi3.so
jlogr-0.1.233.dist-info/RECORD
