Metadata-Version: 2.1
Name: jlogr
Version: 0.1.233
Author: Jesse Williams
